.gitignore
LICENSE.txt
MANIFEST.in
README.md
requirements.txt
setup.py
bin/rapic-client-generator
rapic/__init__.py
rapic/__version__.py
rapic/base.py
rapic/client.py
rapic/exceptions.py
rapic/hook.py
rapic.egg-info/PKG-INFO
rapic.egg-info/SOURCES.txt
rapic.egg-info/dependency_links.txt
rapic.egg-info/not-zip-safe
rapic.egg-info/requires.txt
rapic.egg-info/top_level.txt
rapic/connection/__init__.py
rapic/connection/request.py
rapic/tests/__init__.py
rapic/tests/httpbin.json
rapic/tests/httpbin_2.json
rapic/tests/httpbin_3.json
rapic/tests/httpbin_4.json
rapic/tests/httpbin_5.json
rapic/tests/test_rapic_client.py
rapic/tests/test_rapic_client_hook.py
rapic/tools/__init__.py
rapic/tools/burp.py
rapic/tools/generate.py