Metadata-Version: 2.1
Name: rapic
Version: 0.1.5
Summary: Automatically generate api client libraries/sdk for websites, online services and 3rd party private api.
Home-page: https://github.com/ydaniels/rapic
Author: Yomi D
Author-email: yomid4all@gmail.com
License: MIT
Keywords: rapic web network internet reverse engineering sdk library api client apiclient
Platform: UNKNOWN
Classifier: License :: OSI Approved :: MIT License
Classifier: Programming Language :: Python :: 3.6
